cicdservices/.env
cicdservices/__init__.py
cicdservices/demo.py
cicdservices/src/__init__.py
cicdservices/src/Interfaces/__init__.py
cicdservices/src/Interfaces/git.py
cicdservices/src/Interfaces/interfaces.py
cicdservices/src/classes/__init__.py
cicdservices/src/classes/dataClass.py
cicdservices/src/classes/github.py
cicdservices/src/classes/gitlab.py
cicdservices/src/classes/jenkins.py
cicdservices/src/classes/vercel.py
cicdservices/src/classes/vercelAPI.py
cicdservices/src/utils/__init__.py
cicdservices/src/utils/utils.py
cicdservices/test/__init__.py
cicdservices/test/test_api_vercel.py
cicdservices/test/test_github.py
cicdservices/test/test_gitlab.py
cicdservices/test/test_jenkins.py
cicdservices/test/test_vercel.py
cicdservices-0.0.1.dist-info/METADATA
cicdservices-0.0.1.dist-info/WHEEL
cicdservices-0.0.1.dist-info/top_level.txt
cicdservices-0.0.1.dist-info/RECORD
