Metadata-Version: 2.1
Name: cicdservices
Version: 0.0.1
Summary: CI-CD Services
Home-page: UNKNOWN
Author: Novateva
Author-email: novateva@novateva.com
License: MIT
Platform: UNKNOWN
Requires-Python: >=3.6
